Country_ID/ID.py
Country_ID/__init__.py
Currency_ID-0.0.1.dist-info/LICENCE.txt.txt
Currency_ID-0.0.1.dist-info/METADATA
Currency_ID-0.0.1.dist-info/WHEEL
Currency_ID-0.0.1.dist-info/top_level.txt
Currency_ID-0.0.1.dist-info/RECORD
