Metadata-Version: 2.1
Name: Currency-ID
Version: 0.0.1
Summary: Currency_ID
Home-page: UNKNOWN
Author: Jagadeeswarudu Kattubadi
Author-email: jagat0963@gmail.com
License: UNKNOWN
Keywords: CurrencyConverter,math,mathematics,python tutorial,Currency_ID
Platform: UNKNOWN
Classifier: Development Status :: 1 - Planning
Classifier: Intended Audience :: Developers
Classifier: Programming Language :: Python :: 3
Classifier: Operating System :: Unix
Classifier: Operating System :: MacOS :: MacOS X
Classifier: Operating System :: Microsoft :: Windows
License-File: LICENCE.txt.txt
